{
  "name": "Florence Barker",
  "age": 22,
  "address": {
    "street": "Reja Square",
    "city": "Baceuto",
    "state": "NY",
    "zip": "38936"
  },
  "contact": {
    "phone": "(776) 218-1170",
    "servicePhone": "800627859"
  },
  "birthday": "1964-06-06T12:52:10.415Z",
  "ip": "151.236.80.150",
  "foo": "bar",
  "profile": {
    "about": "Cos cutcuinu ajtumvis edinigah eceto socebol za po fu to fuhil lamfildi ukujobu laol evuzuego emdoc. Cije isewobbo jemapfom cahkahsod jauhu wam awejupoc gav unirah jewa dimvot boko wehpauva zezwir. Ucufikej labup bum felu kitep hakfi ha no daw junifwu wimzekuc woskeg ojo losamu lifombaj imevut kowofes kovlunba. Viewuom ane ze weuwacez kawenu liri naprake cubenuta botmeazu apuref bofnitjeh zothad. Kewip bijsol etna ve paulu ezo taet vucsater vovec gaw pug ferimuko fafo ama map woce. Zadu riz bicca ta tem jop cifus nijelfe iweg tathemen nemima buof wicgug fo ehelubve golaca pe.",
    "bio": "Ijueloice libcoc satlipe ulowoh kanak dewwit kun popouko mun ew abi kaw. No ikiuze ewo hod oclow kuhkaten sidsu ci ijo diriluk up jareron nonu gitilco wizubov cizliogo wimejag ke. Upize ed gorti nowom vonregpo usihuug diuhtuk hoducho wuam ivi puhahka telciwko tuva wignujo obe ceg pizjicim uhejom."
  },
  "apiKey": "40fadd8a98aa5838dd743aae906c474d7f3f70ddea0182762ac00a4d4d65f3a4",
  "currency": {
    "code": "CUP",
    "name": "Cuba Peso"
  }
}